<?xml version="1.0" encoding="UTF-8"?><subLeg xmlns="http://www.xml.gov.hk/schemas/hklm/1.0" xmlns:dcterms="http://purl.org/dc/terms/" xmlns:dc="http://purl.org/dc/elements/1.1/" xmlns:xhtml="http://www.w3.org/1999/xhtml" xmlns:xsi="http://www.w3.org/2001/XMLSchema-instance" xsi:schemaLocation="http://www.xml.gov.hk/schemas/hklm/1.0 https://www.elegislation.gov.hk/schemas/hklm.xsd" xml:lang="en"><meta><docName>Cap. 362 sub. leg. O</docName><docType>cap</docType><docNumber>362O</docNumber><docStatus>In effect</docStatus><dc:identifier>/hk/cap362O!en</dc:identifier><dc:date>2019-12-12</dc:date><dc:subject>legislation</dc:subject><dc:language>en</dc:language><dc:publisher>DoJ</dc:publisher><dc:rights>the Government of the Hong Kong Special Administrative Region</dc:rights></meta><main xml:lang="en" xsi:schemaLocation="http://www.xml.gov.hk/schemas/hklm/1.0 https://www.elegislation.gov.hk/schemas/hklm.xsd"><docTitle id="ID_1438403066848_002" name="shortTitle" reason="inEffect" status="operational" temporalId="shortTitle" startPeriod="2019-12-12">Trade
            Descriptions (Provision of Information on Regulated Electronic Products)
            Order</docTitle><enactingFormula>(<ref href="/hk/cap362/s4">Cap. 362, section
            4</ref>)</enactingFormula><sourceNote>(Enacting provision omitted—<ref href="hk/2019/er6">E.R. 6 of 2019</ref>)<marker role="blank-line"></marker><marker role="blank-line"></marker></sourceNote><commencementNote>[2 March 2009]<sourceNote><inline class="width_3"> </inline><ref href="/hk/2008/ln269">L.N. 269 of 2008</ref></sourceNote></commencementNote><sourceNote>(Format changes—<ref href="hk/2019/er6">E.R. 6 of 2019</ref>)</sourceNote><section id="ID_1438403066864_002" name="s1" reason="omittedAsSpent" startPeriod="2019-12-12" status="omitted" temporalId="s1"><num value="1">1.</num><sourceNote>(Omitted as spent—<ref href="hk/2019/er6">E.R. 6 of 2019</ref>)</sourceNote></section><section id="ID_1438403066864_004" name="s2" reason="inEffect" startPeriod="2019-12-12" status="operational" temporalId="s2"><num value="2">2.</num><heading>Interpretation</heading><subsection id="ID_1438412098730_004" name="1" temporalId="s2_1"><num value="1">(1)</num><leadIn>In this Order, unless the context otherwise requires—</leadIn><def name="DigitalAudioPlayer"><leadIn><term>digital
                        audio
                    player</term>
                        (<term xml:lang="zh-Hant-HK">數碼音響播放器</term>)—</leadIn><paragraph id="ID_1438412098730_019" name="a" temporalId="s2_1_a"><num value="a">(a)</num><content>means any portable device the principal function of which is to play
                        digital audio files in one or more audio encoding formats from any storage
                        medium;</content></paragraph><paragraph id="ID_1438412098746_006" name="b" temporalId="s2_1_b"><num value="b">(b)</num><content>includes the product commonly known as MP3 player;
                        and</content></paragraph><paragraph id="ID_1438412098746_014" name="c" temporalId="s2_1_c"><num value="c">(c)</num><content>does not include portable optical disc player;
                        <sourceNote>(<ref href="/hk/2008/ln169">L.N. 169 of
                        2008</ref>)</sourceNote></content></paragraph></def><def name="DigitalCamcorder"><term>digital
                    camcorder</term>
                    (<term xml:lang="zh-Hant-HK">數碼攝錄機</term>) means any portable device the
                principal function of which is to make a recording in digital format on any medium
                from which a moving image may by any means be reproduced;
                <sourceNote>(<ref href="/hk/2008/ln169">L.N. 169 of
                    2008</ref>)</sourceNote></def><def name="DigitalCamera"><term>digital
                    camera</term>
                    (<term xml:lang="zh-Hant-HK">數碼相機</term>) means any portable device the
                principal function of which is to record and store an image in digital format on any
                medium from which a still image may by any means be reproduced;
                <sourceNote>(<ref href="/hk/2008/ln169">L.N. 169 of
                    2008</ref>)</sourceNote></def><def name="MobilePhone"><leadIn><term>mobile
                        phone</term>
                        (<term xml:lang="zh-Hant-HK">手提電話</term>) means any portable device the
                    principal function of which is for mobile communication through a cellular radio
                    network with—</leadIn><paragraph id="ID_1438412098746_042" name="a" temporalId="s2_1_a"><num value="a">(a)</num><content>standard voice function of a telephone;
                        and
                        <sourceNote>(<ref href="/hk/2008/ln169">L.N. 169 of
                                2008</ref>)</sourceNote></content></paragraph><paragraph id="ID_1438412098746_050" name="b" temporalId="s2_1_b"><num value="b">(b)</num><content>interconnection to the public switched telephone network (PSTN);</content></paragraph></def><def name="PortableMultimediaPlayer"><leadIn><term>portable
                        multimedia
                    player</term>
                        (<term xml:lang="zh-Hant-HK">便攜式多媒體播放器</term>)—</leadIn><paragraph id="ID_1438412098746_064" name="a" temporalId="s2_1_a"><num value="a">(a)</num><content>means any portable device the principal function of which is to play
                        digital multimedia files in one or more media recording formats from any
                        storage
                        medium;</content></paragraph><paragraph id="ID_1438412098746_072" name="b" temporalId="s2_1_b"><num value="b">(b)</num><content>includes the product commonly known as MP4 player;
                        and</content></paragraph><paragraph id="ID_1438412098746_080" name="c" temporalId="s2_1_c"><num value="c">(c)</num><content>does not include portable optical disc player;
                        <sourceNote>(<ref href="/hk/2008/ln169">L.N. 169 of
                        2008</ref>)</sourceNote></content></paragraph></def><def name="RegulatedElectronicProduct"><leadIn><term>regulated
                        electronic
                    product</term>
                        (<term xml:lang="zh-Hant-HK">受規管電子產品</term>) means—</leadIn><paragraph id="ID_1438412098761_012" name="a" temporalId="s2_1_a"><num value="a">(a)</num><content>digital audio player;</content></paragraph><paragraph id="ID_1438412098761_020" name="b" temporalId="s2_1_b"><num value="b">(b)</num><content>digital camcorder;</content></paragraph><paragraph id="ID_1438412098761_028" name="c" temporalId="s2_1_c"><num value="c">(c)</num><content>digital camera;</content></paragraph><paragraph id="ID_1438412098761_036" name="d" temporalId="s2_1_d"><num value="d">(d)</num><content>mobile phone; or</content></paragraph><paragraph id="ID_1438412098761_044" name="e" temporalId="s2_1_e"><num value="e">(e)</num><content>portable multimedia player.</content></paragraph></def></subsection><subsection id="ID_1438412098761_051" name="2" temporalId="s2_2"><num value="2">(2)</num><leadIn>In determining the principal function of a product for the purposes of this section, regard shall be had to—</leadIn><paragraph id="ID_1438412098761_059" name="a" temporalId="s2_2_a"><num value="a">(a)</num><content>the description applied to the product on its package;</content></paragraph><paragraph id="ID_1438412098761_067" name="b" temporalId="s2_2_b"><num value="b">(b)</num><content>the description applied to the product in any document relating to the
                    supply of the product;
                    <sourceNote>(<ref href="/hk/2008/ln169">L.N. 169 of
                        2008</ref>)</sourceNote></content></paragraph><paragraph id="ID_1438412098761_075" name="c" temporalId="s2_2_c"><num value="c">(c)</num><content>the description applied to the product in any promotional material and
                    advertisement concerning the product; and
                    <sourceNote>(<ref href="/hk/2008/ln169">L.N. 169 of
                        2008</ref>)</sourceNote></content></paragraph><paragraph id="ID_1438412098761_083" name="d" temporalId="s2_2_d"><num value="d">(d)</num><content>any other relevant information.
                    <sourceNote>(<ref href="/hk/2008/ln169">L.N. 169 of
                        2008</ref>)</sourceNote></content></paragraph></subsection></section><section id="ID_1438403066879_002" name="s3" reason="inEffect" startPeriod="2019-12-12" status="operational" temporalId="s3"><num value="3">3.</num><heading>Supply to be accompanied by written particulars</heading><subsection id="ID_1438412098964_004" name="1" temporalId="s3_1"><num value="1">(1)</num><content>Any person who supplies any regulated electronic product in the course of trade or business at retail level shall, at the time of supply, issue an invoice or receipt to the person to whom the product is supplied.</content></subsection><subsection id="ID_1438412098980_005" name="1A" temporalId="s3_1A"><num value="1A">(1A)</num><content>Subsection (1) applies only to trade or business conducted on premises being a
                tenement included in the valuation list in force under <ref>section 14</ref> of the
                Rating Ordinance (<ref href="/hk/cap116">Cap. 116</ref>).
                <sourceNote>(<ref href="/hk/2008/ln169">L.N. 169 of
                    2008</ref>)</sourceNote></content></subsection><subsection id="ID_1438412098980_013" name="2" temporalId="s3_2"><num value="2">(2)</num><leadIn>An invoice or receipt issued under subsection (1) shall contain—</leadIn><paragraph id="ID_1438412098995_005" name="a" temporalId="s3_2_a"><num value="a">(a)</num><content>the full name and address of the supplier;</content></paragraph><paragraph id="ID_1438412098995_013" name="b" temporalId="s3_2_b"><num value="b">(b)</num><content>the price at which the product is supplied;</content></paragraph><paragraph id="ID_1438412098995_021" name="c" temporalId="s3_2_c"><num value="c">(c)</num><content>the date of supply;</content></paragraph><paragraph id="ID_1438412098995_029" name="d" temporalId="s3_2_d"><num value="d">(d)</num><content>the brand name of the product;</content></paragraph><paragraph id="ID_1438412098995_037" name="e" temporalId="s3_2_e"><num value="e">(e)</num><content>the model number of the product (if any);</content></paragraph><paragraph id="ID_1438412098995_045" name="f" temporalId="s3_2_f"><num value="f">(f)</num><leadIn>the following information as regards service for the inspection, repair or maintenance of the product—</leadIn><subparagraph id="ID_1438412098995_053" name="i" temporalId="s3_2_f_i"><num value="i">(i)</num><content>such service is available free of charge or such service is not so available, as may be applicable; and</content></subparagraph><subparagraph id="ID_1438412098995_061" name="ii" temporalId="s3_2_f_ii"><num value="ii">(ii)</num><leadIn>where such service is available—</leadIn><subparagraph id="ID_1438412099011_006" name="A" role="subSubParagraph" temporalId="s3_2_f_ii_A"><num value="A">(A)</num><content>subject to subsection (3), the place at which such service is available;</content></subparagraph><subparagraph id="ID_1438412099011_014" name="B" role="subSubParagraph" temporalId="s3_2_f_ii_B"><num value="B">(B)</num><content>the identity of the provider of such service; and</content></subparagraph><subparagraph id="ID_1438412099011_022" name="C" role="subSubParagraph" temporalId="s3_2_f_ii_C"><num value="C">(C)</num><content>the period for which such service is available;
                            <sourceNote>(<ref href="/hk/2008/ln169">L.N. 169 of
                                    2008</ref>)</sourceNote></content></subparagraph></subparagraph></paragraph><paragraph id="ID_1438412099011_029" name="g" temporalId="s3_2_g"><num value="g">(g)</num><content>the place of manufacture of the product or, where the place of manufacture is unknown to the supplier, a statement that the place of manufacture is unknown; and</content></paragraph><paragraph id="ID_1438412099011_037" name="h" temporalId="s3_2_h"><num value="h">(h)</num><content>the information prescribed in relation to the product in column 2 of the <ref>Schedule</ref>.</content></paragraph></subsection><subsection id="ID_1438412099011_044" name="3" temporalId="s3_3"><num value="3">(3)</num><leadIn>For the purposes of subsection <ref>(2)(f)(ii)(A)</ref>, where a service for the
                inspection, repair or maintenance of a product is available in more than one place,
                an invoice or receipt issued under subsection (2) shall at
                        least— <sourceNote>(<ref href="/hk/2008/ln169">L.N. 169 of 2008</ref>)</sourceNote></leadIn><paragraph id="ID_1438412099011_052" name="a" temporalId="s3_3_a"><num value="a">(a)</num><content>where the supplier has made a representation to the purchaser that such
                    service is available in any particular one of those places, contain information
                    on that
                    place;</content></paragraph><paragraph id="ID_1438412099011_060" name="b" temporalId="s3_3_b"><num value="b">(b)</num><leadIn>where the supplier has not made any representation to the purchaser that
                    such service is available in a particular place, contain information on the
                            place— <sourceNote>(<ref href="/hk/2008/ln169">L.N. 169 of 2008</ref>)</sourceNote></leadIn><subparagraph id="ID_1438412099011_068" name="i" temporalId="s3_3_b_i"><num value="i">(i)</num><content>in which it is, having regard to all information available to the
                        supplier, most likely that the purchaser will avail himself of such service;
                        and</content></subparagraph><subparagraph id="ID_1438412099027_007" name="ii" temporalId="s3_3_b_ii"><num value="ii">(ii)</num><content>in which such service is available.
                        <sourceNote>(<ref href="/hk/2008/ln169">L.N. 169 of
                                2008</ref>)</sourceNote></content></subparagraph></paragraph></subsection></section><section id="ID_1438403066895_002" name="s4" reason="inEffect" startPeriod="2019-12-12" status="operational" temporalId="s4"><num value="4">4.</num><heading>Supplier shall retain invoice or receipt for 3 years</heading><subsection id="ID_1438412099058_004" name="1" temporalId="s4_1"><num value="1">(1)</num><content>A supplier shall retain a copy of an invoice or receipt issued by him under <ref>section 3</ref> for a period of not less than 3 years after the date of issue.</content></subsection><subsection id="ID_1438412099058_012" name="2" temporalId="s4_2"><num value="2">(2)</num><content>Any person who contravenes subsection (1) commits an offence and is liable on conviction to a fine at level 2 and imprisonment for 1 month.</content></subsection></section><section id="ID_1438403066895_004" name="s5" reason="inEffect" startPeriod="2019-12-12" status="operational" temporalId="s5"><num value="5">5.</num><heading>Position of auctioneer</heading><subsection id="ID_1438412099089_019" name="1" temporalId="s5_1"><num value="1">(1)</num><leadIn>For the purposes of this Order, where a regulated electronic product is sold by auction—</leadIn><paragraph id="ID_1438412099089_027" name="a" temporalId="s5_1_a"><num value="a">(a)</num><content>the auctioneer shall be regarded as the supplier of the product; and</content></paragraph><paragraph id="ID_1438412099089_035" name="b" temporalId="s5_1_b"><num value="b">(b)</num><content>it shall, in the absence of evidence to the contrary, be presumed to be supplied in the course of trade or business at retail level.</content></paragraph></subsection><subsection id="ID_1438412099089_042" name="2" temporalId="s5_2"><num value="2">(2)</num><leadIn>For the purposes of this Order, where a regulated electronic product is offered for sale by auction, it shall—</leadIn><paragraph id="ID_1438412099089_050" name="a" temporalId="s5_2_a"><num value="a">(a)</num><content>be regarded as being offered for supply by the auctioneer; and</content></paragraph><paragraph id="ID_1438412099089_058" name="b" temporalId="s5_2_b"><num value="b">(b)</num><content>in the absence of evidence to the contrary, be presumed to be offered for supply in the course of trade or business at retail level.</content></paragraph></subsection></section><schedule id="ID_1438403066910_002" name="sch0" reason="inEffect" startPeriod="2019-12-12" status="operational" temporalId="sch0"><num value="0">Schedule</num><note role="crossReferences" type="inline" class="align_right">[<ref href="/hk/cap362O/s3">s. 3</ref>]</note><heading>Prescribed
            Information<marker role="blank-line"></marker><marker role="blank-line"></marker></heading><text><table xmlns="http://www.w3.org/1999/xhtml" class="repeat_header" width="100%">
                <col width="37.212%"></col>
                <col width="6.97%"></col>
                <col width="55.818%"></col>
                <thead>
                    <tr>
                        
                        <td class="cellpadding_bottom_15">
                            
                            
                            <p class="valign_bottom">
                                
                                <center xmlns="http://www.xml.gov.hk/schemas/hklm/1.0">Regulated
                                    electronic<br></br>product</center>
                            </p>
                            
                        </td>
                        
                        <td colspan="2" class="cellpadding_bottom_15">
                            
                            
                            <p class="valign_bottom">
                                
                                <center xmlns="http://www.xml.gov.hk/schemas/hklm/1.0">Information
                                    prescribed for the purposes<br xmlns="http://www.w3.org/1999/xhtml"></br>of
                                        <ref>section
                                        3(2)(h)</ref>
                                    of this
                                    Order</center>
                            </p>
                            
                        </td>
                    </tr>
                </thead>
                <tbody>
                    <tr>
                        <td>
                            <p>Digital audio player</p>
                        </td>
                        <td>
                            <p>(a)</p>
                        </td>
                        <td>
                            <p>memory capacity</p>
                        </td>
                    </tr>
                    <tr>
                        <td></td>
                        <td>
                            <p>(b)</p>
                        </td>
                        <td>
                            <p>availability of radio function</p>
                        </td>
                    </tr>
                    <tr>
                        <td></td>
                        <td>
                            <p>(c)</p>
                        </td>
                        <td>
                            <p>availability of voice recording function</p>
                        </td>
                    </tr>
                    <tr>
                        <td></td>
                        <td>
                            <p>(d)</p>
                        </td>
                        
                        <td class="cellpadding_bottom_10">
                            <p>availability of line-in recording function</p>
                            
                        </td>
                    </tr>
                    <tr>
                        <td>
                            <p>Digital camcorder</p>
                        </td>
                        <td>
                            <p>(a)</p>
                        </td>
                        <td>
                            <p>optical zoom range of the lens</p>
                        </td>
                    </tr>
                    <tr>
                        <td></td>
                        <td>
                            <p>(b)</p>
                        </td>
                        <td>
                            <p>the type and capacity of storage media</p>
                        </td>
                    </tr>
                    <tr>
                        <td></td>
                        <td>
                            <p>(c)</p>
                        </td>
                        <td>
                            <p>resolution for still picture in terms of pixels</p>
                        </td>
                    </tr>
                    <tr>
                        <td></td>
                        <td>
                            <p>(d)</p>
                        </td>
                        
                        <td class="cellpadding_bottom_10">
                            <p>the type and storage capacity of support memory card (if
                                provided)</p>
                            
                        </td>
                    </tr>
                    <tr>
                        <td>
                            <p>Digital camera</p>
                        </td>
                        <td>
                            <p>(a)</p>
                        </td>
                        <td>
                            <p>resolution of the camera in terms of pixels</p>
                        </td>
                    </tr>
                    <tr>
                        <td></td>
                        <td>
                            <p>(b)</p>
                        </td>
                        <td>
                            <p>the type and storage capacity of support memory card (if provided)
                            </p>
                        </td>
                    </tr>
                    <tr>
                        <td></td>
                        <td>
                            <p>(c)</p>
                        </td>
                        <td>
                            <p>(where the camera is fitted with built-in lens or the lens is sold
                                together with the camera as a single item) optical zoom range of the
                                lens</p>
                        </td>
                    </tr>
                    <tr>
                        <td></td>
                        <td>
                            <p>(d)</p>
                        </td>
                        
                        <td class="cellpadding_bottom_10">
                            <p>(where the camera is fitted with built-in lens or the lens is sold
                                together with the camera as a single item) maximum aperture of the
                                lens</p>
                            
                        </td>
                    </tr>
                    <tr>
                        <td>
                            <p>Mobile phone</p>
                        </td>
                        <td>
                            <p>(a)</p>
                        </td>
                        <td>
                            <p>network frequency or operating frequency or band</p>
                        </td>
                    </tr>
                    <tr>
                        <td></td>
                        <td>
                            <p>(b)</p>
                        </td>
                        <td>
                            <p>the type and storage capacity of support memory card (if
                                provided)</p>
                        </td>
                    </tr>
                    <tr>
                        <td></td>
                        <td>
                            <p>(c)</p>
                        </td>
                        <td>
                            <p>data transfer/network connectivity protocol</p>
                        </td>
                    </tr>
                    <tr>
                        <td></td>
                        <td>
                            <p>(d)</p>
                        </td>
                        
                        <td class="cellpadding_bottom_10">
                            <p>(where the phone has a built-in camera) resolution of the camera in
                                terms of pixels</p>
                            
                        </td>
                    </tr>
                    
                    <tr>
                        <td>
                            <p>Portable multimedia player</p>
                        </td>
                        <td>
                            <p>(a)</p>
                        </td>
                        <td>
                            <p>memory capacity</p>
                        </td>
                    </tr>
                    <tr>
                        <td></td>
                        <td>
                            <p>(b)</p>
                        </td>
                        <td>
                            <p>availability of radio function</p>
                        </td>
                    </tr>
                    <tr>
                        <td></td>
                        <td>(c)</td>
                        <td>
                            <p>availability of voice recording function</p>
                        </td>
                    </tr>
                    <tr>
                        <td></td>
                        <td>(d)</td>
                        <td>
                            <p>availability of line-in recording function</p>
                        </td>
                    </tr>
                </tbody>
            </table><sourceNote>(<ref href="/hk/2008/ln169">L.N. 169 of
            2008</ref>)</sourceNote></text></schedule></main></subLeg>