<?xml version="1.0" encoding="UTF-8"?><subLeg xmlns="http://www.xml.gov.hk/schemas/hklm/1.0" xmlns:dc="http://purl.org/dc/elements/1.1/" xmlns:xhtml="http://www.w3.org/1999/xhtml" xmlns:xsi="http://www.w3.org/2001/XMLSchema-instance" xmlns:dcterms="http://purl.org/dc/terms/" xsi:schemaLocation="http://www.xml.gov.hk/schemas/hklm/1.0 https://www.elegislation.gov.hk/schemas/hklm.xsd" xml:lang="en"><meta><docName>Cap. 432 sub. leg. B</docName><docType>cap</docType><docNumber>432B</docNumber><docStatus>Not adopted as the Laws of the HKSAR</docStatus><dc:identifier>/hk/cap432B!en</dc:identifier><dc:date>1997-07-01</dc:date><dc:subject>legislation</dc:subject><dc:language>en</dc:language><dc:publisher>DoJ</dc:publisher><dc:rights>the Government of the Hong Kong Special Administrative Region</dc:rights></meta><main xml:lang="en" xsi:schemaLocation="http://www.xml.gov.hk/schemas/hklm/1.0 https://www.elegislation.gov.hk/schemas/hklm.xsd"><docTitle id="ID_1438403193286_001" name="shortTitle" reason="notAdopted" status="other" temporalId="shortTitle" startPeriod="1997-07-01">Boundary
            and Election Commission (Electoral Procedure) (Geographical Constituencies)
            Regulation</docTitle><sourceNote class="align_center">(Not adopted as the Laws of the HKSAR)</sourceNote><editorialNote id="ID_1541024194588_001">
            <content>(See Decision of the Standing Committee of the National People’s Congress on
                Treatment of the Laws Previously in Force in Hong Kong in accordance with Article
                160 of the Basic Law of the Hong Kong Special Administrative Region of the People’s
                Republic of China (Instrument <ref href="/hk/a206">A206</ref> in this
                database))</content>
        </editorialNote><part id="ID_1438403193286_003" name="P1" reason="notAdopted" startPeriod="1997-07-01" status="other" temporalId="P1"><num value="1">Part I</num><sourceNote>(Not adopted as the Laws of the HKSAR)</sourceNote><section id="ID_1438403193302_001" name="s1" reason="notAdopted" startPeriod="1997-07-01" status="other" temporalId="s1"><num value="1">1.</num><sourceNote>(Not adopted as the Laws of the HKSAR)</sourceNote></section><section id="ID_1438403193302_003" name="s2" reason="notAdopted" startPeriod="1997-07-01" status="other" temporalId="s2"><num value="2">2.</num><sourceNote>(Not adopted as the Laws of the HKSAR)</sourceNote></section></part><part id="ID_1438403193317_001" name="P2" reason="notAdopted" startPeriod="1997-07-01" status="other" temporalId="P2"><num value="2">Part II</num><sourceNote>(Not adopted as the Laws of the HKSAR)</sourceNote><section id="ID_1438403193333_001" name="s3" reason="notAdopted" startPeriod="1997-07-01" status="other" temporalId="s3"><num value="3">3.</num><sourceNote>(Not adopted as the Laws of the HKSAR)</sourceNote></section><section id="ID_1438403193333_003" name="s4" reason="notAdopted" startPeriod="1997-07-01" status="other" temporalId="s4"><num value="4">4.</num><sourceNote>(Not adopted as the Laws of the HKSAR)</sourceNote></section><section id="ID_1438403193349_001" name="s5" reason="notAdopted" startPeriod="1997-07-01" status="other" temporalId="s5"><num value="5">5.</num><sourceNote>(Not adopted as the Laws of the HKSAR)</sourceNote></section><section id="ID_1438403193349_003" name="s6" reason="notAdopted" startPeriod="1997-07-01" status="other" temporalId="s6"><num value="6">6.</num><sourceNote>(Not adopted as the Laws of the HKSAR)</sourceNote></section><section id="ID_1438403193349_005" name="s7" reason="notAdopted" startPeriod="1997-07-01" status="other" temporalId="s7"><num value="7">7.</num><sourceNote>(Not adopted as the Laws of the HKSAR)</sourceNote></section><section id="ID_1438403193364_002" name="s8" reason="notAdopted" startPeriod="1997-07-01" status="other" temporalId="s8"><num value="8">8.</num><sourceNote>(Not adopted as the Laws of the HKSAR)</sourceNote></section><section id="ID_1438403193364_004" name="s9" reason="notAdopted" startPeriod="1997-07-01" status="other" temporalId="s9"><num value="9">9.</num><sourceNote>(Not adopted as the Laws of the HKSAR)</sourceNote></section><section id="ID_1438403193380_002" name="s10" reason="notAdopted" startPeriod="1997-07-01" status="other" temporalId="s10"><num value="10">10.</num><sourceNote>(Not adopted as the Laws of the HKSAR)</sourceNote></section><section id="ID_1438403193380_004" name="s11" reason="notAdopted" startPeriod="1997-07-01" status="other" temporalId="s11"><num value="11">11.</num><sourceNote>(Not adopted as the Laws of the HKSAR)</sourceNote></section><section id="ID_1438403193395_002" name="s12" reason="notAdopted" startPeriod="1997-07-01" status="other" temporalId="s12"><num value="12">12.</num><sourceNote>(Not adopted as the Laws of the HKSAR)</sourceNote></section><section id="ID_1438403193411_001" name="s13" reason="notAdopted" startPeriod="1997-07-01" status="other" temporalId="s13"><num value="13">13.</num><sourceNote>(Not adopted as the Laws of the HKSAR)</sourceNote></section><section id="ID_1438403193411_003" name="s14" reason="notAdopted" startPeriod="1997-07-01" status="other" temporalId="s14"><num value="14">14.</num><sourceNote>(Not adopted as the Laws of the HKSAR)</sourceNote></section><section id="ID_1438403193411_005" name="s15" reason="notAdopted" startPeriod="1997-07-01" status="other" temporalId="s15"><num value="15">15.</num><sourceNote>(Not adopted as the Laws of the HKSAR)</sourceNote></section><section id="ID_1438403193427_002" name="s16" reason="notAdopted" startPeriod="1997-07-01" status="other" temporalId="s16"><num value="16">16.</num><sourceNote>(Not adopted as the Laws of the HKSAR)</sourceNote></section><section id="ID_1438403193427_004" name="s16A" reason="notAdopted" startPeriod="1997-07-01" status="other" temporalId="s16A"><num value="16A">16A.</num><sourceNote>(Not adopted as the Laws of the HKSAR)</sourceNote></section><section id="ID_1438403193442_002" name="s16B" reason="notAdopted" startPeriod="1997-07-01" status="other" temporalId="s16B"><num value="16B">16B.</num><sourceNote>(Not adopted as the Laws of the HKSAR)</sourceNote></section><section id="ID_1438403193442_004" name="s16C" reason="notAdopted" startPeriod="1997-07-01" status="other" temporalId="s16C"><num value="16C">16C.</num><sourceNote>(Not adopted as the Laws of the HKSAR)</sourceNote></section><section id="ID_1438403193458_002" name="s16D" reason="notAdopted" startPeriod="1997-07-01" status="other" temporalId="s16D"><num value="16D">16D.</num><sourceNote>(Not adopted as the Laws of the HKSAR)</sourceNote></section></part><part id="ID_1438403193458_004" name="P3" reason="notAdopted" startPeriod="1997-07-01" status="other" temporalId="P3"><num value="3">Part III</num><sourceNote>(Not adopted as the Laws of the HKSAR)</sourceNote><section id="ID_1438403193473_002" name="s17" reason="notAdopted" startPeriod="1997-07-01" status="other" temporalId="s17"><num value="17">17.</num><sourceNote>(Not adopted as the Laws of the HKSAR)</sourceNote></section><section id="ID_1438403193473_004" name="s18" reason="notAdopted" startPeriod="1997-07-01" status="other" temporalId="s18"><num value="18">18.</num><sourceNote>(Not adopted as the Laws of the HKSAR)</sourceNote></section><section id="ID_1438403193489_002" name="s19" reason="notAdopted" startPeriod="1997-07-01" status="other" temporalId="s19"><num value="19">19.</num><sourceNote>(Not adopted as the Laws of the HKSAR)</sourceNote></section><section id="ID_1438403193489_004" name="s20" reason="notAdopted" startPeriod="1997-07-01" status="other" temporalId="s20"><num value="20">20.</num><sourceNote>(Not adopted as the Laws of the HKSAR)</sourceNote></section><section id="ID_1438403193505_002" name="s21" reason="notAdopted" startPeriod="1997-07-01" status="other" temporalId="s21"><num value="21">21.</num><sourceNote>(Not adopted as the Laws of the HKSAR)</sourceNote></section><section id="ID_1438403193505_004" name="s22" reason="notAdopted" startPeriod="1997-07-01" status="other" temporalId="s22"><num value="22">22.</num><sourceNote>(Not adopted as the Laws of the HKSAR)</sourceNote></section><section id="ID_1438403193520_002" name="s23" reason="notAdopted" startPeriod="1997-07-01" status="other" temporalId="s23"><num value="23">23.</num><sourceNote>(Not adopted as the Laws of the HKSAR)</sourceNote></section><section id="ID_1438403193520_004" name="s24" reason="notAdopted" startPeriod="1997-07-01" status="other" temporalId="s24"><num value="24">24.</num><sourceNote>(Not adopted as the Laws of the HKSAR)</sourceNote></section><section id="ID_1438403193536_002" name="s25" reason="notAdopted" startPeriod="1997-07-01" status="other" temporalId="s25"><num value="25">25.</num><sourceNote>(Not adopted as the Laws of the HKSAR)</sourceNote></section><section id="ID_1438403193536_004" name="s26" reason="notAdopted" startPeriod="1997-07-01" status="other" temporalId="s26"><num value="26">26.</num><sourceNote>(Not adopted as the Laws of the HKSAR)</sourceNote></section><section id="ID_1438403193551_002" name="s27" reason="notAdopted" startPeriod="1997-07-01" status="other" temporalId="s27"><num value="27">27.</num><sourceNote>(Not adopted as the Laws of the HKSAR)</sourceNote></section><section id="ID_1438403193551_004" name="s28" reason="notAdopted" startPeriod="1997-07-01" status="other" temporalId="s28"><num value="28">28.</num><sourceNote>(Not adopted as the Laws of the HKSAR)</sourceNote></section><section id="ID_1438403193567_002" name="s29" reason="notAdopted" startPeriod="1997-07-01" status="other" temporalId="s29"><num value="29">29.</num><sourceNote>(Not adopted as the Laws of the HKSAR)</sourceNote></section><section id="ID_1438403193567_004" name="s30" reason="notAdopted" startPeriod="1997-07-01" status="other" temporalId="s30"><num value="30">30.</num><sourceNote>(Not adopted as the Laws of the HKSAR)</sourceNote></section><section id="ID_1438403193583_002" name="s31" reason="notAdopted" startPeriod="1997-07-01" status="other" temporalId="s31"><num value="31">31.</num><sourceNote>(Not adopted as the Laws of the HKSAR)</sourceNote></section><section id="ID_1438403193583_004" name="s32" reason="notAdopted" startPeriod="1997-07-01" status="other" temporalId="s32"><num value="32">32.</num><sourceNote>(Not adopted as the Laws of the HKSAR)</sourceNote></section><section id="ID_1438403193598_002" name="s33" reason="notAdopted" startPeriod="1997-07-01" status="other" temporalId="s33"><num value="33">33.</num><sourceNote>(Not adopted as the Laws of the HKSAR)</sourceNote></section><section id="ID_1438403193598_004" name="s34" reason="notAdopted" startPeriod="1997-07-01" status="other" temporalId="s34"><num value="34">34.</num><sourceNote>(Not adopted as the Laws of the HKSAR)</sourceNote></section><section id="ID_1438403193614_002" name="s35" reason="notAdopted" startPeriod="1997-07-01" status="other" temporalId="s35"><num value="35">35.</num><sourceNote>(Not adopted as the Laws of the HKSAR)</sourceNote></section><section id="ID_1438403193629_002" name="s36" reason="notAdopted" startPeriod="1997-07-01" status="other" temporalId="s36"><num value="36">36.</num><sourceNote>(Not adopted as the Laws of the HKSAR)</sourceNote></section><section id="ID_1438403193645_002" name="s37" reason="notAdopted" startPeriod="1997-07-01" status="other" temporalId="s37"><num value="37">37.</num><sourceNote>(Not adopted as the Laws of the HKSAR)</sourceNote></section><section id="ID_1438403193645_004" name="s37A" reason="notAdopted" startPeriod="1997-07-01" status="other" temporalId="s37A"><num value="37A">37A.</num><sourceNote>(Not adopted as the Laws of the HKSAR)</sourceNote></section><section id="ID_1438403193661_002" name="s38" reason="notAdopted" startPeriod="1997-07-01" status="other" temporalId="s38"><num value="38">38.</num><sourceNote>(Not adopted as the Laws of the HKSAR)</sourceNote></section><section id="ID_1438403193661_004" name="s39" reason="notAdopted" startPeriod="1997-07-01" status="other" temporalId="s39"><num value="39">39.</num><sourceNote>(Not adopted as the Laws of the HKSAR)</sourceNote></section><section id="ID_1438403193676_002" name="s40" reason="notAdopted" startPeriod="1997-07-01" status="other" temporalId="s40"><num value="40">40.</num><sourceNote>(Not adopted as the Laws of the HKSAR)</sourceNote></section><section id="ID_1438403193676_004" name="s41" reason="notAdopted" startPeriod="1997-07-01" status="other" temporalId="s41"><num value="41">41.</num><sourceNote>(Not adopted as the Laws of the HKSAR)</sourceNote></section></part><part id="ID_1438403193692_002" name="P4" reason="notAdopted" startPeriod="1997-07-01" status="other" temporalId="P4"><num value="4">Part IV</num><sourceNote>(Not adopted as the Laws of the HKSAR)</sourceNote><section id="ID_1438403193692_004" name="s42" reason="notAdopted" startPeriod="1997-07-01" status="other" temporalId="s42"><num value="42">42.</num><sourceNote>(Not adopted as the Laws of the HKSAR)</sourceNote></section><section id="ID_1438403193707_002" name="s43" reason="notAdopted" startPeriod="1997-07-01" status="other" temporalId="s43"><num value="43">43.</num><sourceNote>(Not adopted as the Laws of the HKSAR)</sourceNote></section><section id="ID_1438403193707_004" name="s44" reason="notAdopted" startPeriod="1997-07-01" status="other" temporalId="s44"><num value="44">44.</num><sourceNote>(Not adopted as the Laws of the HKSAR)</sourceNote></section><section id="ID_1438403193723_002" name="s45" reason="notAdopted" startPeriod="1997-07-01" status="other" temporalId="s45"><num value="45">45.</num><sourceNote>(Not adopted as the Laws of the HKSAR)</sourceNote></section><section id="ID_1438403193723_004" name="s46" reason="notAdopted" startPeriod="1997-07-01" status="other" temporalId="s46"><num value="46">46.</num><sourceNote>(Not adopted as the Laws of the HKSAR)</sourceNote></section><section id="ID_1438403193739_001" name="s47" reason="notAdopted" startPeriod="1997-07-01" status="other" temporalId="s47"><num value="47">47.</num><sourceNote>(Not adopted as the Laws of the HKSAR)</sourceNote></section><section id="ID_1438403193739_003" name="s48" reason="notAdopted" startPeriod="1997-07-01" status="other" temporalId="s48"><num value="48">48.</num><sourceNote>(Not adopted as the Laws of the HKSAR)</sourceNote></section><section id="ID_1438403193754_001" name="s49" reason="notAdopted" startPeriod="1997-07-01" status="other" temporalId="s49"><num value="49">49.</num><sourceNote>(Not adopted as the Laws of the HKSAR)</sourceNote></section><section id="ID_1438403193754_003" name="s50" reason="notAdopted" startPeriod="1997-07-01" status="other" temporalId="s50"><num value="50">50.</num><sourceNote>(Not adopted as the Laws of the HKSAR)</sourceNote></section><section id="ID_1438403193770_001" name="s51" reason="notAdopted" startPeriod="1997-07-01" status="other" temporalId="s51"><num value="51">51.</num><sourceNote>(Not adopted as the Laws of the HKSAR)</sourceNote></section><section id="ID_1438403193785_001" name="s52" reason="notAdopted" startPeriod="1997-07-01" status="other" temporalId="s52"><num value="52">52.</num><sourceNote>(Not adopted as the Laws of the HKSAR)</sourceNote></section><section id="ID_1438403193785_003" name="s53" reason="notAdopted" startPeriod="1997-07-01" status="other" temporalId="s53"><num value="53">53.</num><sourceNote>(Not adopted as the Laws of the HKSAR)</sourceNote></section></part><part id="ID_1438403193817_001" name="P5" reason="notAdopted" startPeriod="1997-07-01" status="other" temporalId="P5"><num value="5">Part V</num><sourceNote>(Not adopted as the Laws of the HKSAR)</sourceNote><section id="ID_1438403193817_003" name="s54" reason="notAdopted" startPeriod="1997-07-01" status="other" temporalId="s54"><num value="54">54.</num><sourceNote>(Not adopted as the Laws of the HKSAR)</sourceNote></section><section id="ID_1438403193832_002" name="s55" reason="notAdopted" startPeriod="1997-07-01" status="other" temporalId="s55"><num value="55">55.</num><sourceNote>(Not adopted as the Laws of the HKSAR)</sourceNote></section><section id="ID_1438403193832_004" name="s56" reason="notAdopted" startPeriod="1997-07-01" status="other" temporalId="s56"><num value="56">56.</num><sourceNote>(Not adopted as the Laws of the HKSAR)</sourceNote></section><section id="ID_1438403193848_002" name="s57" reason="notAdopted" startPeriod="1997-07-01" status="other" temporalId="s57"><num value="57">57.</num><sourceNote>(Not adopted as the Laws of the HKSAR)</sourceNote></section></part><part id="ID_1438403193848_004" name="P6" reason="notAdopted" startPeriod="1997-07-01" status="other" temporalId="P6"><num value="6">Part VI</num><sourceNote>(Not adopted as the Laws of the HKSAR)</sourceNote><section id="ID_1438403193863_001" name="s58" reason="notAdopted" startPeriod="1997-07-01" status="other" temporalId="s58"><num value="58">58.</num><sourceNote>(Not adopted as the Laws of the HKSAR)</sourceNote></section><section id="ID_1438403193863_003" name="s59" reason="notAdopted" startPeriod="1997-07-01" status="other" temporalId="s59"><num value="59">59.</num><sourceNote>(Not adopted as the Laws of the HKSAR)</sourceNote></section><section id="ID_1438403193879_001" name="s60" reason="notAdopted" startPeriod="1997-07-01" status="other" temporalId="s60"><num value="60">60.</num><sourceNote>(Not adopted as the Laws of the HKSAR)</sourceNote></section><section id="ID_1438403193910_001" name="s61" reason="notAdopted" startPeriod="1997-07-01" status="other" temporalId="s61"><num value="61">61.</num><sourceNote>(Not adopted as the Laws of the HKSAR)</sourceNote></section><section id="ID_1438403193910_003" name="s62" reason="notAdopted" startPeriod="1997-07-01" status="other" temporalId="s62"><num value="62">62.</num><sourceNote>(Not adopted as the Laws of the HKSAR)</sourceNote></section><section id="ID_1438403193926_001" name="s63" reason="notAdopted" startPeriod="1997-07-01" status="other" temporalId="s63"><num value="63">63.</num><sourceNote>(Not adopted as the Laws of the HKSAR)</sourceNote></section><section id="ID_1438403193926_003" name="s64" reason="notAdopted" startPeriod="1997-07-01" status="other" temporalId="s64"><num value="64">64.</num><sourceNote>(Not adopted as the Laws of the HKSAR)</sourceNote></section></part><part id="ID_1438403193941_002" name="P7" reason="notAdopted" startPeriod="1997-07-01" status="other" temporalId="P7"><num value="7">Part VII</num><sourceNote>(Not adopted as the Laws of the HKSAR)</sourceNote><section id="ID_1438403193957_001" name="s65" reason="notAdopted" startPeriod="1997-07-01" status="other" temporalId="s65"><num value="65">65.</num><sourceNote>(Not adopted as the Laws of the HKSAR)</sourceNote></section><section id="ID_1438403193973_001" name="s66" reason="notAdopted" startPeriod="1997-07-01" status="other" temporalId="s66"><num value="66">66.</num><sourceNote>(Not adopted as the Laws of the HKSAR)</sourceNote></section><section id="ID_1438403193973_003" name="s67" reason="notAdopted" startPeriod="1997-07-01" status="other" temporalId="s67"><num value="67">67.</num><sourceNote>(Not adopted as the Laws of the HKSAR)</sourceNote></section><section id="ID_1438403193988_001" name="s68" reason="notAdopted" startPeriod="1997-07-01" status="other" temporalId="s68"><num value="68">68.</num><sourceNote>(Not adopted as the Laws of the HKSAR)</sourceNote></section><section id="ID_1438403193988_003" name="s69" reason="notAdopted" startPeriod="1997-07-01" status="other" temporalId="s69"><num value="69">69.</num><sourceNote>(Not adopted as the Laws of the HKSAR)</sourceNote></section><section id="ID_1438403194004_001" name="s70" reason="notAdopted" startPeriod="1997-07-01" status="other" temporalId="s70"><num value="70">70.</num><sourceNote>(Not adopted as the Laws of the HKSAR)</sourceNote></section><section id="ID_1438403194004_003" name="s71" reason="notAdopted" startPeriod="1997-07-01" status="other" temporalId="s71"><num value="71">71.</num><sourceNote>(Not adopted as the Laws of the HKSAR)</sourceNote></section><section id="ID_1438403194019_001" name="s72" reason="notAdopted" startPeriod="1997-07-01" status="other" temporalId="s72"><num value="72">72.</num><sourceNote>(Not adopted as the Laws of the HKSAR)</sourceNote></section><section id="ID_1438403194035_002" name="s73" reason="notAdopted" startPeriod="1997-07-01" status="other" temporalId="s73"><num value="73">73.</num><sourceNote>(Not adopted as the Laws of the HKSAR)</sourceNote></section><section id="ID_1438403194051_002" name="s74" reason="notAdopted" startPeriod="1997-07-01" status="other" temporalId="s74"><num value="74">74.</num><sourceNote>(Not adopted as the Laws of the HKSAR)</sourceNote></section><section id="ID_1438403194066_002" name="s75" reason="notAdopted" startPeriod="1997-07-01" status="other" temporalId="s75"><num value="75">75.</num><sourceNote>(Not adopted as the Laws of the HKSAR)</sourceNote></section><section id="ID_1438403194066_004" name="s76" reason="notAdopted" startPeriod="1997-07-01" status="other" temporalId="s76"><num value="76">76.</num><sourceNote>(Not adopted as the Laws of the HKSAR)</sourceNote></section><section id="ID_1438403194082_002" name="s77" reason="notAdopted" startPeriod="1997-07-01" status="other" temporalId="s77"><num value="77">77.</num><sourceNote>(Not adopted as the Laws of the HKSAR)</sourceNote></section><section id="ID_1438403194082_004" name="s78" reason="notAdopted" startPeriod="1997-07-01" status="other" temporalId="s78"><num value="78">78.</num><sourceNote>(Not adopted as the Laws of the HKSAR)</sourceNote></section><section id="ID_1438403194097_002" name="s79" reason="notAdopted" startPeriod="1997-07-01" status="other" temporalId="s79"><num value="79">79.</num><sourceNote>(Not adopted as the Laws of the HKSAR)</sourceNote></section></part><schedule id="ID_1438403194097_004" name="sch0" reason="notAdopted" startPeriod="1997-07-01" status="other" temporalId="sch0"><num value="0">Schedule</num><sourceNote>(Not adopted as the Laws of the HKSAR)</sourceNote></schedule></main></subLeg>